KaliLinuxWuxianShentouCeshiRumenZhinan/README.md
KaliLinuxWuxianShentouCeshiRumenZhinan/__init__.py
KaliLinuxWuxianShentouCeshiRumenZhinan/__main__.py
KaliLinuxWuxianShentouCeshiRumenZhinan/file.epub
KaliLinuxWuxianShentouCeshiRumenZhinan/index.html
KaliLinuxWuxianShentouCeshiRumenZhinan/css/__init__.py
KaliLinuxWuxianShentouCeshiRumenZhinan/css/annotations.css
KaliLinuxWuxianShentouCeshiRumenZhinan/css/main.css
KaliLinuxWuxianShentouCeshiRumenZhinan/css/normalize.css
KaliLinuxWuxianShentouCeshiRumenZhinan/css/popup.css
KaliLinuxWuxianShentouCeshiRumenZhinan/font/__init__.py
KaliLinuxWuxianShentouCeshiRumenZhinan/font/fontello.eot
KaliLinuxWuxianShentouCeshiRumenZhinan/font/fontello.svg
KaliLinuxWuxianShentouCeshiRumenZhinan/font/fontello.ttf
KaliLinuxWuxianShentouCeshiRumenZhinan/font/fontello.woff
KaliLinuxWuxianShentouCeshiRumenZhinan/img/__init__.py
KaliLinuxWuxianShentouCeshiRumenZhinan/img/annotator-glyph-sprite.png
KaliLinuxWuxianShentouCeshiRumenZhinan/img/annotator-icon-sprite.png
KaliLinuxWuxianShentouCeshiRumenZhinan/img/apple-touch-icon.png
KaliLinuxWuxianShentouCeshiRumenZhinan/img/cancelfullscreen.png
KaliLinuxWuxianShentouCeshiRumenZhinan/img/close.png
KaliLinuxWuxianShentouCeshiRumenZhinan/img/fullscreen.png
KaliLinuxWuxianShentouCeshiRumenZhinan/img/loader.gif
KaliLinuxWuxianShentouCeshiRumenZhinan/img/menu-icon.png
KaliLinuxWuxianShentouCeshiRumenZhinan/img/save.png
KaliLinuxWuxianShentouCeshiRumenZhinan/img/saved.png
KaliLinuxWuxianShentouCeshiRumenZhinan/img/settings-s.png
KaliLinuxWuxianShentouCeshiRumenZhinan/img/settings.png
KaliLinuxWuxianShentouCeshiRumenZhinan/img/star.png
KaliLinuxWuxianShentouCeshiRumenZhinan/js/__init__.py
KaliLinuxWuxianShentouCeshiRumenZhinan/js/epub.js
KaliLinuxWuxianShentouCeshiRumenZhinan/js/epub.min.js
KaliLinuxWuxianShentouCeshiRumenZhinan/js/epub.min.map
KaliLinuxWuxianShentouCeshiRumenZhinan/js/hooks.min.js
KaliLinuxWuxianShentouCeshiRumenZhinan/js/hooks.min.map
kali_linux_wuxian_shentou_ceshi_rumen_zhinan-2024.3.1.0.dist-info/METADATA
kali_linux_wuxian_shentou_ceshi_rumen_zhinan-2024.3.1.0.dist-info/WHEEL
kali_linux_wuxian_shentou_ceshi_rumen_zhinan-2024.3.1.0.dist-info/entry_points.txt
kali_linux_wuxian_shentou_ceshi_rumen_zhinan-2024.3.1.0.dist-info/top_level.txt
kali_linux_wuxian_shentou_ceshi_rumen_zhinan-2024.3.1.0.dist-info/RECORD
